arches_graphql_client/__init__.py
arches_graphql_client/client.py
arches_graphql_client/concept.py
arches_graphql_client/dask.py
arches_graphql_client/definition.py
arches_graphql_client/loader.py
arches_graphql_client/mapper.py
arches_graphql_client/resource.py
arches_graphql_client/resource_model.py
arches_graphql_client/utils.py
arches_graphql_client-0.0.8.dist-info/METADATA
arches_graphql_client-0.0.8.dist-info/WHEEL
arches_graphql_client-0.0.8.dist-info/top_level.txt
arches_graphql_client-0.0.8.dist-info/RECORD
